tello_sdk/Tello.py
tello_sdk/__init__.py
tello_sdk/telloLive.py
tello_sdk-2.4.2.dist-info/LICENCE
tello_sdk-2.4.2.dist-info/METADATA
tello_sdk-2.4.2.dist-info/WHEEL
tello_sdk-2.4.2.dist-info/top_level.txt
tello_sdk-2.4.2.dist-info/RECORD
