Metadata-Version: 2.1
Name: tello-sdk
Version: 2.4.2
Summary: Python SDK fro the Tello EDU and RMTT drones, with all commands and more.
Author: ErnGusMik
Project-URL: Homepage, https://github.com/ErnGusMik/python-tello
Keywords: tello,drone,sdk,python,python3,rmtt,edu,telloedu,tello-rmtt,tello-edu,sdk
Classifier: Development Status :: 5 - Production/Stable
Classifier: Intended Audience :: Developers
Classifier: Topic :: Software Development :: Build Tools
Classifier: License :: OSI Approved :: MIT License
Classifier: Programming Language :: Python :: 3
Requires-Python: >=3.6.0
License-File: LICENCE
Requires-Dist: sentry-sdk
